AI_Module/__init__.py
FH_AI_TOOL-1.0.0.dist-info/METADATA
FH_AI_TOOL-1.0.0.dist-info/WHEEL
FH_AI_TOOL-1.0.0.dist-info/top_level.txt
FH_AI_TOOL-1.0.0.dist-info/RECORD
