Metadata-Version: 2.1
Name: FH_AI_TOOL
Version: 1.0.0
Summary: FH,FJ Vision AI SYSTEM LIB
Home-page: https://github.com/LEE-pyt/AI_Module.git
Author: LEE_DH
Author-email: ldh9616@nate.com
Keywords: FH_AI,FH_AI_TOOL,FH_AI_LIB,python tutorial,pypi
Classifier: Programming Language :: Python :: 3.8
Classifier: Programming Language :: Python :: 3.9
Classifier: Programming Language :: Python :: 3.10
Classifier: Programming Language :: Python :: 3.11
Requires-Python: >=3.8
Requires-Dist: tqdm
Requires-Dist: pandas
Requires-Dist: scikit-learn
Requires-Dist: torch ==2.0.1
Requires-Dist: torchvision ==0.15.2
Requires-Dist: onnx
Requires-Dist: onnxruntime
Requires-Dist: pycocotools
Requires-Dist: anomalib
